{
  "buildCommand" : "build",
  "configuredTargets" : [
    {
      "guid" : "abf513be97a92394f44af4574be76a9349cc7edd7b846a377b35c959b34fc351"
    }
  ],
  "continueBuildingAfterErrors" : false,
  "enableIndexBuildArena" : false,
  "hideShellScriptEnvironment" : false,
  "parameters" : {
    "action" : "build",
    "activeArchitecture" : "arm64",
    "activeRunDestination" : {
      "disableOnlyActiveArch" : false,
      "platform" : "iphonesimulator",
      "sdk" : "iphonesimulator14.5",
      "sdkVariant" : "iphonesimulator",
      "supportedArchitectures" : [
        "arm64",
        "x86_64"
      ],
      "targetArchitecture" : "arm64"
    },
    "arenaInfo" : {
      "buildIntermediatesPath" : "",
      "buildProductsPath" : "",
      "derivedDataPath" : "/Users/alexandr/Library/Developer/Xcode/DerivedData",
      "indexDataStoreFolderPath" : "/Users/alexandr/Library/Developer/Xcode/DerivedData/Memory_Card_Game-gsmdhnxcfkakjlaoqtcuxtjhefis/Index/DataStore",
      "indexEnableDataStore" : true,
      "indexPCHPath" : "/Users/alexandr/Library/Developer/Xcode/DerivedData/Memory_Card_Game-gsmdhnxcfkakjlaoqtcuxtjhefis/Index/PrecompiledHeaders",
      "pchPath" : ""
    },
    "configurationName" : "Debug",
    "overrides" : {
      "synthesized" : {
        "table" : {
          "ASSETCATALOG_FILTER_FOR_DEVICE_MODEL" : "iPhone12,5",
          "ASSETCATALOG_FILTER_FOR_DEVICE_OS_VERSION" : "14.5",
          "BUILD_ACTIVE_RESOURCES_ONLY" : "YES",
          "ENABLE_PREVIEWS" : "NO",
          "TARGET_DEVICE_IDENTIFIER" : "D5917CBD-EF1D-4883-8FE3-150E4BB92B39",
          "TARGET_DEVICE_MODEL" : "iPhone12,5",
          "TARGET_DEVICE_OS_VERSION" : "14.5",
          "TARGET_DEVICE_PLATFORM_NAME" : "iphonesimulator"
        }
      }
    }
  },
  "schemeCommand" : "launch",
  "shouldCollectMetrics" : false,
  "showNonLoggedProgress" : true,
  "useDryRun" : false,
  "useImplicitDependencies" : true,
  "useLegacyBuildLocations" : false,
  "useParallelTargets" : true
}